fixedfloat_api/FixedFloat.py
fixedfloat_api/__init__.py
fixedfloat_api-1.0.3.dist-info/LICENSE
fixedfloat_api-1.0.3.dist-info/METADATA
fixedfloat_api-1.0.3.dist-info/WHEEL
fixedfloat_api-1.0.3.dist-info/top_level.txt
fixedfloat_api-1.0.3.dist-info/RECORD
