Metadata-Version: 2.1
Name: fixedfloat-api
Version: 1.0.3
Summary: FixedFloat API
Home-page: https://github.com/GuilhermeFischer/fixedfloat_api
Author: Guilherme A. Fischer
Author-email: <gfx.fischer@gmail.com>
Keywords: api,crypto,exchange,fixedfloat,bitcoin,ethereum
Classifier: Development Status :: 5 - Production/Stable
Classifier: Intended Audience :: Developers
Classifier: Programming Language :: Python :: 3
Classifier: Operating System :: OS Independent
Classifier: License :: OSI Approved :: MIT License
License-File: LICENSE
Requires-Dist: requests
